{
  "title": "Lord of the Rings API Scraper",
  "description": "Fetch comprehensive data from The One API to rule them all. Scrape books, movies, characters, quotes, and chapters from J.R.R. Tolkien's epic universe with advanced filtering and sorting options.",
  "type": "object",
  "schemaVersion": 1,
  "properties": {
    "entity": {
      "title": "Entity Type",
      "type": "string",
      "description": "Choose which type of data to scrape from Tolkien's universe.",
      "editor": "select",
      "enum": ["book", "movie", "character", "quote", "chapter"],
      "enumTitles": ["Books", "Movies", "Characters", "Quotes", "Chapters"],
      "default": "character"
    },
    "maxResults": {
      "title": "Maximum Results",
      "type": "integer",
      "description": "Maximum number of results to fetch across all pages.",
      "minimum": 1,
      "maximum": 1000,
      "default": 100,
      "editor": "number"
    },
    "sort": {
      "title": "Sort order",
      "type": "string",
      "description": "Sort results by field and direction (e.g., 'name:asc', 'runtimeInMinutes:desc').",
      "editor": "select",
      "enum": ["name:asc", "name:desc", "runtimeInMinutes:asc", "runtimeInMinutes:desc", "budgetInMillions:desc", "academyAwardWins:desc"],
      "default": "name:asc"
    },
    "characterName": {
      "title": "Character Name",
      "type": "string",
      "description": "Filter characters by name (substring match, case-insensitive).",
      "editor": "textfield"
    },
    "movieName": {
      "title": "Movie Name",
      "type": "string",
      "description": "Filter movies by name (substring match).",
      "editor": "textfield"
    },
    "quoteDialog": {
      "title": "Quote Dialog",
      "type": "string",
      "description": "Filter quotes by dialog text (substring match).",
      "editor": "textfield"
    },
    "chapterName": {
      "title": "Chapter Name",
      "type": "string",
      "description": "Filter chapters by chapter name (substring match).",
      "editor": "textfield"
    },
    "bookName": {
      "title": "Book Name",
      "type": "string",
      "description": "Filter books by name (substring match).",
      "editor": "textfield"
    },
    "customFilters": {
      "title": "Custom Filters",
      "type": "object",
      "description": "Advanced custom filters using MongoDB query syntax (e.g., {\"name\": \"/foot/i\", \"height\": {\"$exists\": true}}).",
      "editor": "json"
    }
  },
  "required": ["entity"],
  "additionalProperties": true
}
